ZizhuZhangxianshengGongzhonggaoBeifenVol1/README.md
ZizhuZhangxianshengGongzhonggaoBeifenVol1/__init__.py
ZizhuZhangxianshengGongzhonggaoBeifenVol1/__main__.py
ZizhuZhangxianshengGongzhonggaoBeifenVol1/file.epub
ZizhuZhangxianshengGongzhonggaoBeifenVol1/index.html
ZizhuZhangxianshengGongzhonggaoBeifenVol1/css/__init__.py
ZizhuZhangxianshengGongzhonggaoBeifenVol1/css/annotations.css
ZizhuZhangxianshengGongzhonggaoBeifenVol1/css/main.css
ZizhuZhangxianshengGongzhonggaoBeifenVol1/css/normalize.css
ZizhuZhangxianshengGongzhonggaoBeifenVol1/css/popup.css
ZizhuZhangxianshengGongzhonggaoBeifenVol1/font/__init__.py
ZizhuZhangxianshengGongzhonggaoBeifenVol1/font/fontello.eot
ZizhuZhangxianshengGongzhonggaoBeifenVol1/font/fontello.svg
ZizhuZhangxianshengGongzhonggaoBeifenVol1/font/fontello.ttf
ZizhuZhangxianshengGongzhonggaoBeifenVol1/font/fontello.woff
ZizhuZhangxianshengGongzhonggaoBeifenVol1/img/__init__.py
ZizhuZhangxianshengGongzhonggaoBeifenVol1/img/annotator-glyph-sprite.png
ZizhuZhangxianshengGongzhonggaoBeifenVol1/img/annotator-icon-sprite.png
ZizhuZhangxianshengGongzhonggaoBeifenVol1/img/apple-touch-icon.png
ZizhuZhangxianshengGongzhonggaoBeifenVol1/img/cancelfullscreen.png
ZizhuZhangxianshengGongzhonggaoBeifenVol1/img/close.png
ZizhuZhangxianshengGongzhonggaoBeifenVol1/img/fullscreen.png
ZizhuZhangxianshengGongzhonggaoBeifenVol1/img/loader.gif
ZizhuZhangxianshengGongzhonggaoBeifenVol1/img/menu-icon.png
ZizhuZhangxianshengGongzhonggaoBeifenVol1/img/save.png
ZizhuZhangxianshengGongzhonggaoBeifenVol1/img/saved.png
ZizhuZhangxianshengGongzhonggaoBeifenVol1/img/settings-s.png
ZizhuZhangxianshengGongzhonggaoBeifenVol1/img/settings.png
ZizhuZhangxianshengGongzhonggaoBeifenVol1/img/star.png
ZizhuZhangxianshengGongzhonggaoBeifenVol1/js/__init__.py
ZizhuZhangxianshengGongzhonggaoBeifenVol1/js/epub.js
ZizhuZhangxianshengGongzhonggaoBeifenVol1/js/epub.min.js
ZizhuZhangxianshengGongzhonggaoBeifenVol1/js/epub.min.map
ZizhuZhangxianshengGongzhonggaoBeifenVol1/js/hooks.min.js
zizhu_zhangxiansheng_gongzhonggao_beifen_vol1-2022.10.10.0.dist-info/METADATA
zizhu_zhangxiansheng_gongzhonggao_beifen_vol1-2022.10.10.0.dist-info/WHEEL
zizhu_zhangxiansheng_gongzhonggao_beifen_vol1-2022.10.10.0.dist-info/entry_points.txt
zizhu_zhangxiansheng_gongzhonggao_beifen_vol1-2022.10.10.0.dist-info/top_level.txt
zizhu_zhangxiansheng_gongzhonggao_beifen_vol1-2022.10.10.0.dist-info/RECORD
